source_iter/__init__.py
source_iter/service_csv.py
source_iter/service_jsonl.py
source_iter-0.25.1.dist-info/LICENSE
source_iter-0.25.1.dist-info/METADATA
source_iter-0.25.1.dist-info/WHEEL
source_iter-0.25.1.dist-info/top_level.txt
source_iter-0.25.1.dist-info/RECORD
